openstb/i18n/__init__.py
openstb/i18n/hatch_hooks.py
openstb/i18n/py.typed
openstb/i18n/support.py
openstb_i18n-1.1.0.dist-info/METADATA
openstb_i18n-1.1.0.dist-info/WHEEL
openstb_i18n-1.1.0.dist-info/entry_points.txt
openstb_i18n-1.1.0.dist-info/RECORD
