Metadata-Version: 2.4
Name: openstb-i18n
Version: 1.1.0
Summary: Internationalisation support for openSTB projects
Requires-Python: >=3.11
Provides-Extra: dev
Requires-Dist: pytest; extra == 'dev'
Requires-Dist: ruff; extra == 'dev'
Provides-Extra: test
Requires-Dist: pytest; extra == 'test'
